analysta_index/__init__.py
analysta_index/indexer.py
analysta_index/document_loaders/AnalystaCSVLoader.py
analysta_index/document_loaders/AnalystaConfluenceLoader.py
analysta_index/document_loaders/AnalystaDirectoryLoader.py
analysta_index/document_loaders/AnalystaExcelLoader.py
analysta_index/document_loaders/AnalystaGitRepoLoader.py
analysta_index/document_loaders/AnalystaTableLoader.py
analysta_index/document_loaders/__init__.py
analysta_index/document_loaders/constants.py
analysta_index/document_loaders/utils.py
analysta_index/interfaces/__init__.py
analysta_index/interfaces/kwextractor.py
analysta_index/interfaces/llm_processor.py
analysta_index/interfaces/loaders.py
analysta_index/interfaces/splitters.py
analysta_index/llms/__init__.py
analysta_index/llms/analysta.py
analysta_index/retrievers/AnalystaRetriever.py
analysta_index/retrievers/__init__.py
analysta_index/tools/__init__.py
analysta_index/tools/git.py
analysta_index/tools/log.py
analysta_indexer-0.1.0.dist-info/LICENSE
analysta_indexer-0.1.0.dist-info/METADATA
analysta_indexer-0.1.0.dist-info/WHEEL
analysta_indexer-0.1.0.dist-info/top_level.txt
analysta_indexer-0.1.0.dist-info/RECORD
