Metadata-Version: 2.1
Name: analysta_indexer
Version: 0.1.0
Summary: Extension of Langchain loaders, llms and retrievers for Analysta
Author-email: Artem Rozumenko <support@analysta.ai>
Project-URL: Homepage, https://analysta.ai
Project-URL: Issues, https://github.com/analysta-ai/indexer/issues
Classifier: Programming Language :: Python :: 3
Classifier: License :: OSI Approved :: Apache Software License
Classifier: Operating System :: OS Independent
Requires-Python: >=3.7
License-File: LICENSE
Requires-Dist: langchain ==0.0.343
Requires-Dist: keybert ==0.8.3
Requires-Dist: charset-normalizer ==3.3.2
Requires-Dist: unstructured ==0.11.2
Requires-Dist: unstructured-pytesseract ==0.3.12
Requires-Dist: unstructured-inference ==0.7.17
Requires-Dist: python-pptx ==0.6.23
Requires-Dist: pdf2image ==1.16.3
Requires-Dist: pikepdf ==8.7.1
Requires-Dist: pypdf ==3.17.1
Requires-Dist: pdfminer.six ==20221105
Requires-Dist: opencv-python ==4.8.1.78
Requires-Dist: pandas ==2.1.3
Requires-Dist: python-docx ==1.1.0
Requires-Dist: openpyxl ==3.1.2
Requires-Dist: markdown ==3.5.1
Requires-Dist: beautifulsoup4 ==4.12.2
Requires-Dist: gensim ==4.3.2
Requires-Dist: chromadb ==0.4.1
Requires-Dist: openai ==1.3.7
Requires-Dist: tiktoken ==0.5.2
Requires-Dist: atlassian-python-api ==3.41.4
Requires-Dist: markdownify ==0.11.6
Requires-Dist: python-dotenv ==1.0.0
Requires-Dist: dulwich ==0.21.6
Requires-Dist: paramiko ==3.3.1
Requires-Dist: urllib3 ==1.26.15
Requires-Dist: requests ==2.31.0
Requires-Dist: certifi ==2023.11.17
